dns_services_gateway/__init__.py
dns_services_gateway/auth.py
dns_services_gateway/cli.py
dns_services_gateway/client.py
dns_services_gateway/config.py
dns_services_gateway/dnssec.py
dns_services_gateway/domain.py
dns_services_gateway/exceptions.py
dns_services_gateway/forwarding.py
dns_services_gateway/models.py
dns_services_gateway/nameservers.py
dns_services_gateway/records.py
dns_services_gateway/templates/__init__.py
dns_services_gateway/templates/cli.py
dns_services_gateway/templates/records/__init__.py
dns_services_gateway/templates/records/groups.py
dns_services_gateway/templates/records/manager.py
dns_services_gateway/templates/records/validator.py
dns_services_gateway/templates/variables/__init__.py
dns_services_gateway/templates/variables/manager.py
dns_services_gateway-0.9.6.dist-info/LICENSE
dns_services_gateway-0.9.6.dist-info/METADATA
dns_services_gateway-0.9.6.dist-info/WHEEL
dns_services_gateway-0.9.6.dist-info/entry_points.txt
dns_services_gateway-0.9.6.dist-info/top_level.txt
dns_services_gateway-0.9.6.dist-info/RECORD
