Metadata-Version: 2.1
Name: dns-services-gateway
Version: 0.9.6
Summary: A Python gateway for DNS.services API
Home-page: https://github.com/mikl0s/dns.services
Author: DNS Services Gateway Team
Project-URL: Bug Tracker, https://github.com/mikl0s/dns.services/issues
Classifier: Development Status :: 4 - Beta
Classifier: Intended Audience :: Developers
Classifier: License :: OSI Approved :: MIT License
Classifier: Programming Language :: Python :: 3
Classifier: Programming Language :: Python :: 3.12
Requires-Python: >=3.12
License-File: LICENSE
Requires-Dist: requests>=2.31.0
Requires-Dist: python-dotenv>=1.0.0
Requires-Dist: pydantic>=2.0.0
Requires-Dist: typing-extensions>=4.8.0
Requires-Dist: click>=8.0.0
Requires-Dist: PyJWT>=2.0.0
Requires-Dist: python-dateutil>=2.8.2
Provides-Extra: cli
Requires-Dist: rich>=13.7.0; extra == "cli"
